rivian/__init__.py
rivian/ble.py
rivian/const.py
rivian/exceptions.py
rivian/py.typed
rivian/rivian.py
rivian/schemas/charging.graphql
rivian/schemas/gateway.graphql
rivian/schemas/orders.graphql
rivian/utils.py
rivian/ws_monitor.py
rivian_python_client-1.4.1.dist-info/METADATA
rivian_python_client-1.4.1.dist-info/WHEEL
rivian_python_client-1.4.1.dist-info/RECORD
