Metadata-Version: 2.3
Name: rivian-python-client
Version: 1.4.1
Summary: Rivian API Client (Unofficial)
License: MIT
Author: Brian Retterer
Author-email: bretterer@gmail.com
Requires-Python: >=3.9,<3.14
Classifier: License :: OSI Approved :: MIT License
Classifier: Programming Language :: Python :: 3
Classifier: Programming Language :: Python :: 3.9
Classifier: Programming Language :: Python :: 3.10
Classifier: Programming Language :: Python :: 3.11
Classifier: Programming Language :: Python :: 3.12
Classifier: Programming Language :: Python :: 3.13
Provides-Extra: ble
Requires-Dist: aiohttp (>=3.0.0)
Requires-Dist: backports-strenum (>=1.2.4,<2.0.0) ; python_version < "3.11"
Requires-Dist: bleak (>=0.21,<2.0.0) ; extra == "ble"
Requires-Dist: cryptography (>=41.0.1,<46.0)
Requires-Dist: dbus-fast (>=2.11.0,<3.0.0) ; (sys_platform == "linux") and (extra == "ble")
